{
	"configurations" : 
	[
		{
			"directories" : 
			[
				{
					"build" : ".",
					"hasInstallRule" : true,
					"jsonFile" : "directory-.-Release-ba409180bbb753523548.json",
					"minimumCMakeVersion" : 
					{
						"string" : "3.12"
					},
					"projectIndex" : 0,
					"source" : ".",
					"targetIndexes" : 
					[
						0,
						1,
						2,
						3,
						4,
						5
					]
				}
			],
			"name" : "Release",
			"projects" : 
			[
				{
					"directoryIndexes" : 
					[
						0
					],
					"name" : "orbslam3",
					"targetIndexes" : 
					[
						0,
						1,
						2,
						3,
						4,
						5
					]
				}
			],
			"targets" : 
			[
				{
					"directoryIndex" : 0,
					"id" : "mono::@6890427a1f51a3e7e1df",
					"jsonFile" : "target-mono-Release-77163a68a5c3ac50dcb2.json",
					"name" : "mono",
					"projectIndex" : 0
				},
				{
					"directoryIndex" : 0,
					"id" : "orbslam3_uninstall::@6890427a1f51a3e7e1df",
					"jsonFile" : "target-orbslam3_uninstall-Release-9511f21eece87e0ab7ef.json",
					"name" : "orbslam3_uninstall",
					"projectIndex" : 0
				},
				{
					"directoryIndex" : 0,
					"id" : "rgbd::@6890427a1f51a3e7e1df",
					"jsonFile" : "target-rgbd-Release-6c9723919058e0975c22.json",
					"name" : "rgbd",
					"projectIndex" : 0
				},
				{
					"directoryIndex" : 0,
					"id" : "stereo::@6890427a1f51a3e7e1df",
					"jsonFile" : "target-stereo-Release-c71a60478d7929036328.json",
					"name" : "stereo",
					"projectIndex" : 0
				},
				{
					"directoryIndex" : 0,
					"id" : "stereo-inertial::@6890427a1f51a3e7e1df",
					"jsonFile" : "target-stereo-inertial-Release-2d1dadf293c52ab2d5d4.json",
					"name" : "stereo-inertial",
					"projectIndex" : 0
				},
				{
					"directoryIndex" : 0,
					"id" : "uninstall::@6890427a1f51a3e7e1df",
					"jsonFile" : "target-uninstall-Release-731bf8e9151e6feaf484.json",
					"name" : "uninstall",
					"projectIndex" : 0
				}
			]
		}
	],
	"kind" : "codemodel",
	"paths" : 
	{
		"build" : "/home/phamthanhbien/colcon_ws/src/build/orbslam3",
		"source" : "/home/phamthanhbien/colcon_ws/src/orbslam3_ros2"
	},
	"version" : 
	{
		"major" : 2,
		"minor" : 4
	}
}
